CoinMktCap/__init__.py
CoinMktCap/core.py
CoinMktCap-0.1.0.dist-info/LICENSE
CoinMktCap-0.1.0.dist-info/METADATA
CoinMktCap-0.1.0.dist-info/WHEEL
CoinMktCap-0.1.0.dist-info/top_level.txt
CoinMktCap-0.1.0.dist-info/RECORD
