Metadata-Version: 2.1
Name: CoinMktCap
Version: 0.1.0
Summary: Python wrapper for CoinMarketCap API
Home-page: https://github.com/sarthakkimtani/CoinMktCap
Author: Sarthak Kimtani
Author-email: sarthakkimtani123@gmail.com
License: MIT
Keywords: cryptocurrency,API,coinmarketcap,BTC,Bitcoin,LTC,Litecoin,XRP,Ripple,ETH,Ethereum 
Platform: UNKNOWN
Classifier: License :: OSI Approved :: MIT License
Classifier: Development Status :: 5 - Production/Stable
Classifier: Intended Audience :: Developers
Classifier: Programming Language :: Python
Classifier: Programming Language :: Python :: 2.7
Classifier: Programming Language :: Python :: 3.6
Classifier: Topic :: Software Development :: Libraries :: Python Modules
Requires-Python: >=3.6
License-File: LICENSE
Requires-Dist: requests
